{
    "c_factor": 0.03592,
    "e_mj/kg": 13.1,
    "heat_flux_kW/m^2": 25.0,
    "grid": true,
    "separation_mm": 25.0,
    "initial_mass_g": 18.489,
    "orientation": "Horizontal",
    "surface_area_cm^2": 88.4,
    "date": "2013-09-25T15:42:17",
    "operator": "Shields",
    "director": "Butler",
    "comments": "DuPont carpet #6 composite 20 oz;\nedge frame w/grid + wire;\n conditioned at 50 to 55% RH; room RH ~32%\n",
    "specimen_number": NaN,
    "events": [
        {
            "time": 316,
            "event": "Start Test"
        },
        {
            "time": 406,
            "event": "Ignition"
        },
        {
            "time": 706,
            "event": "Flame Out"
        }
    ],
    "test_start_time_s": 316,
    "time_to_ignition_s": 406,
    "time_to_flameout_s": 706
}